python_rust_module/sum.py
python_rust_module-0.1.1.dist-info/METADATA
python_rust_module-0.1.1.dist-info/WHEEL
python_rust_module-0.1.1.dist-info/RECORD
