Metadata-Version: 2.1
Name: python_rust_module
Version: 0.1.1
Summary: 
Author: wellshs
Author-email: wellshs999@gmail.com
Requires-Python: >=3.11,<4.0
Classifier: Programming Language :: Python :: 3
Classifier: Programming Language :: Python :: 3.11
Requires-Dist: maturin (>=1.1.0,<2.0.0)
